CPred/CPred_NN.py
CPred/CPred_main.py
CPred/FeatureEngineering.py
CPred/__init__.py
CPred/Data/Unimod_modifications.xlsx
CPred/Data/Models/CPred_model_v1.h5
CPred-0.1.4.dist-info/LICENSE.txt
CPred-0.1.4.dist-info/METADATA
CPred-0.1.4.dist-info/WHEEL
CPred-0.1.4.dist-info/top_level.txt
CPred-0.1.4.dist-info/RECORD
