Metadata-Version: 2.1
Name: CPred
Version: 0.1.4
Summary: CPred: A deep learning framework for predicting the charge state distribution in modified and unmodified peptides in ESI
Author-email: Frédérique Vilenne <frederique.vilenne@uhasselt.be>
License: Apache License
Project-URL: Homepage, https://github.com/VilenneFrederique/CPred
Keywords: Deep learning,proteomics,Charge state
Classifier: Programming Language :: Python :: 3
Classifier: License :: OSI Approved :: Apache Software License
Requires-Python: >=3.9
License-File: LICENSE.txt
Requires-Dist: docutils
Requires-Dist: pandas>=2.2
Requires-Dist: numpy>=1.26
Requires-Dist: regex>=2023.12.25
Requires-Dist: openpyxl>=3.1.2
Requires-Dist: tensorflow>=2.15
Requires-Dist: keras<3
Requires-Dist: scikit-learn>=1.4
Requires-Dist: keras_tuner>=1.4.6
Requires-Dist: fastparquet>=2023.10.1
